{
  "search_bid_guardian": {
    "tagline": "Automatically reduce Google Ads bids by 20% for underperforming campaigns (ROAS < 3)",
    "required_features": {
      "roas_threshold": 3,
      "bid_adjustment_percent": -20
    },
    "success_metrics": {
      "campaigns_updated": ">=1",
      "avg_roas_improvement": ">0"
    },
    "timeline": {
      "start": [
        "pull GA4 metrics"
      ],
      "next": [
        "identify campaigns below ROAS threshold"
      ],
      "end": [
        "apply bid adjustments and log changes"
      ]
    },
    "tools": {
      "ga4.pull": {
        "outputs": {
          "campaign_roas": "ROAS by campaign for the specified date range"
        }
      },
      "gads.updatebid": {
        "inputs": {
          "campaign_id": "ID of campaign to adjust",
          "bid_adjustment_percent": "Percentage change to apply (negative for reduction)"
        }
      }
    },
    "observer_hints": {
      "sinks": [
        {
          "type": "jsonl"
        }
      ]
    }
  }
}